pyroutelib3/__init__.py
pyroutelib3/distance.py
pyroutelib3/kd.py
pyroutelib3/nx.py
pyroutelib3/protocols.py
pyroutelib3/py.typed
pyroutelib3/router.py
pyroutelib3/simple_graph.py
pyroutelib3/test_distance.py
pyroutelib3/test_kd.py
pyroutelib3/test_nx.py
pyroutelib3/test_router.py
pyroutelib3/osm/__init__.py
pyroutelib3/osm/graph.py
pyroutelib3/osm/live_graph.py
pyroutelib3/osm/profile.py
pyroutelib3/osm/reader.py
pyroutelib3/osm/test_graph.py
pyroutelib3/osm/test_live_graph.py
pyroutelib3/osm/test_profile.py
pyroutelib3/osm/test_reader.py
pyroutelib3/osm/pbf/__init__.py
pyroutelib3/osm/pbf/fileformat_pb2.py
pyroutelib3/osm/pbf/fileformat_pb2.pyi
pyroutelib3/osm/pbf/osmformat_pb2.py
pyroutelib3/osm/pbf/osmformat_pb2.pyi
pyroutelib3/osm/test_fixtures/simple_graph.osm
pyroutelib3/osm/test_fixtures/simple_graph.osm.bz2
pyroutelib3/osm/test_fixtures/simple_graph.osm.gz
pyroutelib3/osm/test_fixtures/simple_graph.osm.pbf
pyroutelib3/osm/test_fixtures/tile_1.osm
pyroutelib3/osm/test_fixtures/tile_2.osm
pyroutelib3/osm/test_fixtures/tile_base.osm
pyroutelib3-2.0.0.dist-info/LICENSE.txt
pyroutelib3-2.0.0.dist-info/WHEEL
pyroutelib3-2.0.0.dist-info/METADATA
pyroutelib3-2.0.0.dist-info/RECORD
