Metadata-Version: 2.1
Name: pyroutelib3
Version: 2.0.0
Summary: Simple routing over OpenStreetMap data
Author-email: Mikołaj Kuranowski <mkuranowski+pypackages@gmail.com>
Requires-Python: >=3.8, <4
Classifier: Development Status :: 5 - Production/Stable
Classifier: License :: OSI Approved :: GNU General Public License v3 or later (GPLv3+)
Classifier: Operating System :: OS Independent
Classifier: Programming Language :: Python :: 3 :: Only
Classifier: Topic :: Scientific/Engineering :: GIS
Classifier: Topic :: Software Development :: Libraries :: Python Modules
Requires-Dist: typing_extensions ~= 4.0
Requires-Dist: protobuf ~= 5.27
Requires-Dist: filelock ~= 3.15
Project-URL: Documentation, https://pyroutelib3.readthedocs.io/
Project-URL: Home, https://github.com/MKuranowski/pyroutelib3
Project-URL: Source, https://github.com/MKuranowski/pyroutelib3
Project-URL: Tracker, https://github.com/MKuranowski/pyroutelib3/issues
